oldnumeric/__init__.py
oldnumeric/alter_code1.py
oldnumeric/alter_code2.py
oldnumeric/array_printer.py
oldnumeric/arrayfns.py
oldnumeric/compat.py
oldnumeric/fft.py
oldnumeric/fix_default_axis.py
oldnumeric/functions.py
oldnumeric/linear_algebra.py
oldnumeric/ma.py
oldnumeric/matrix.py
oldnumeric/misc.py
oldnumeric/mlab.py
oldnumeric/precision.py
oldnumeric/random_array.py
oldnumeric/rng.py
oldnumeric/rng_stats.py
oldnumeric/typeconv.py
oldnumeric/ufuncs.py
oldnumeric/user_array.py
oldnumeric-1.0.4.dist-info/DESCRIPTION.rst
oldnumeric-1.0.4.dist-info/METADATA
oldnumeric-1.0.4.dist-info/RECORD
oldnumeric-1.0.4.dist-info/WHEEL
oldnumeric-1.0.4.dist-info/metadata.json
oldnumeric-1.0.4.dist-info/top_level.txt
