Metadata-Version: 2.0
Name: oldnumeric
Version: 1.0.4
Summary: The oldnumeric numpy package
Home-page: UNKNOWN
Author: xoviat
Author-email: xoviat@noreply.users.github.com
License: UNKNOWN
Platform: UNKNOWN
Requires-Dist: numpy
